LICENSE
MANIFEST.in
README.rst
setup.py
bash_powerprompt.egg-info/PKG-INFO
bash_powerprompt.egg-info/SOURCES.txt
bash_powerprompt.egg-info/dependency_links.txt
bash_powerprompt.egg-info/requires.txt
bash_powerprompt.egg-info/top_level.txt
powerprompt/__init__.py
powerprompt/core.py
powerprompt/bin/bashpowerprompt.py