Metadata-Version: 1.1
Name: bash-powerprompt
Version: 0.1.0
Summary: Powerful dynamic bash prompt inspired by Vim Powerline
Home-page: https://github.com/MrHaas/bash-powerprompt
Author: Arjan de Pooter
Author-email: mail@arjandepooter.nl
License: UNKNOWN
Platform: UNKNOWN
Classifier: Development Status :: 2 - Pre-Alpha
Classifier: Environment :: Console
Classifier: Intended Audience :: System Administrators
Classifier: License :: OSI Approved :: MIT License
Classifier: Operating System :: Unix
Classifier: Programming Language :: Python
Classifier: Topic :: System :: Shells
